{
	"info": {
		"_postman_id": "d3c64b08-0a9c-4f4e-b3cc-fb66269585af",
		"name": "auth-exp-api",
		"schema": "https://schema.getpostman.com/json/collection/v2.1.0/collection.json",
		"_exporter_id": "23513349"
	},
	"item": [
		{
			"name": "authenticate user",
			"request": {
				"method": "POST",
				"header": [
					{
						"key": "Content-Type",
						"value": "application/json",
						"type": "text"
					}
				],
				"body": {
					"mode": "raw",
					"raw": "{\r\n    \"email\" : \"viewer@coldchain.com\",\r\n    \"password\": \"hashedpassword2\"\r\n}\r\n",
					"options": {
						"raw": {
							"language": "json"
						}
					}
				},
				"url": {
					"raw": "http://localhost:8088/exp/auth/login",
					"protocol": "http",
					"host": [
						"localhost"
					],
					"port": "8088",
					"path": [
						"exp",
						"auth",
						"login"
					]
				}
			},
			"response": []
		},
		{
			"name": "add user-signup",
			"request": {
				"method": "POST",
				"header": [
					{
						"key": "Content-Type",
						"value": "application/json",
						"type": "text"
					}
				],
				"body": {
					"mode": "raw",
					"raw": "{\r\n    \"email\" : \"Rasta@coldchain.com\",\r\n    \"password\": \"12345\",\r\n    \"fullname\": \"Rasta\",\r\n    \"role\":\"Viewer\"\r\n}\r\n",
					"options": {
						"raw": {
							"language": "json"
						}
					}
				},
				"url": {
					"raw": "http://localhost:8088/exp/auth/signUp",
					"protocol": "http",
					"host": [
						"localhost"
					],
					"port": "8088",
					"path": [
						"exp",
						"auth",
						"signUp"
					]
				}
			},
			"response": []
		}
	]
}